{
    "TitleLeftHand0": {
        "Rotation_EaseType": 0,
        "Rotation_IsActive": false,
        "Rotation_IsReturnToOrigin": false,
        "Rotation_MaxTime": 1.0,
        "Rotation_ReturnEaseType": 0,
        "Rotation_ReturnMaxTime": 1.0,
        "Rotation_endValue": [
            0.0,
            0.0,
            0.0
        ],
        "Scale_EaseType": 0,
        "Scale_IsActive": false,
        "Scale_IsReturnToOrigin": false,
        "Scale_MaxTime": 1.0,
        "Scale_ReturnEaseType": 0,
        "Scale_ReturnMaxTime": 1.0,
        "Scale_endValue": [
            1.0,
            1.0,
            1.0
        ],
        "Translation_EaseType": 0,
        "Translation_IsActive": true,
        "Translation_IsLookAtDirection": false,
        "Translation_IsReturnToOrigin": true,
        "Translation_MaxTime": 0.09000000357627869,
        "Translation_RailFileName": "",
        "Translation_ReturnEaseType": 21,
        "Translation_ReturnMaxTime": 0.09000000357627869,
        "Translation_UseRail": false,
        "Translation_endValue": [
            0.0,
            0.0,
            4.0
        ],
        "returnStartTime": 0.0,
        "startTime": 1.2000000476837158,
        "timeMode": 1
    }
}
